{
  "id": "dotproperty-ph-warehouse-factory-for-sale-in-vasra-metr",
  "source": "dotproperty-ph",
  "url": "https://www.dotproperty.com.ph/ads/warehouse-factory-for-sale-in-vasra-metro-manila_ca666caeacf3-637e-2412-72dd-db632089",
  "scraped_at": "2026-05-15T01:06:17.959493Z",
  "first_seen_at": "2026-05-04T06:54:12.500955Z",
  "expires_at": "2026-05-22T01:06:17.959493Z",
  "status": "incomplete",
  "listing": {
    "title": "786 square meters Warehouse for Sale in Quezon City, Metro Manila",
    "sqm": 786.0,
    "dock_doors": null,
    "clear_height_m": null,
    "address": "Metro Manila, Quezon City, Vasra",
    "region": "NCR",
    "lat": null,
    "lng": null,
    "price_php": 461206000.0,
    "price_unit": "total",
    "agent_name": "Zobelle88 Brokerage",
    "agent_phone": null,
    "raw_extras": {
      "listing_type": "warehouses-for-sale",
      "area_raw": "Usable area: 786 m2",
      "price_raw": "Sale: ₱ 461,206,000"
    }
  },
  "enriched": {
    "corridor_distances_km": {},
    "peza_zone_km": null,
    "flood_risk": null
  },
  "missing_required": [
    "dock_doors"
  ]
}